abd_distances-1.0.4.dist-info/METADATA
abd_distances-1.0.4.dist-info/WHEEL
abd_distances/vectors.py
abd_distances/strings.pyi
abd_distances/simd.py
abd_distances/simd.pyi
abd_distances/vectors.pyi
abd_distances/__init__.py
abd_distances/py.typed
abd_distances/strings.py
abd_distances/abd_distances.abi3.so
abd_distances-1.0.4.dist-info/RECORD
