Metadata-Version: 2.4
Name: abd-distances
Version: 1.0.4
Classifier: Programming Language :: Rust
Classifier: Programming Language :: Python :: Implementation :: CPython
Classifier: Programming Language :: Python :: Implementation :: PyPy
Requires-Dist: numpy
Summary: Distance functions: A drop-in replacement for, and a super-set of the scipy.spatial.distance module.
Keywords: distance,metric,simd
Requires-Python: >=3.9
